myredditdl/__init__.py
myredditdl/__main__.py
myredditdl/config.ini
myredditdl/config_handler.py
myredditdl/console_args.py
myredditdl/defaults.py
myredditdl/downloader.py
myredditdl/file_handler.py
myredditdl/gui.py
myredditdl/item.py
myredditdl/metadata_handler.py
myredditdl/myredditdl.py
myredditdl/reddit_client.py
myredditdl/terminal.py
myredditdl/utils.py
myredditdl/__pycache__/__init__.cpython-39.pyc
myredditdl/metadata/.gitkeep
myredditdl-0.0.7.dist-info/LICENSE
myredditdl-0.0.7.dist-info/METADATA
myredditdl-0.0.7.dist-info/WHEEL
myredditdl-0.0.7.dist-info/entry_points.txt
myredditdl-0.0.7.dist-info/top_level.txt
myredditdl-0.0.7.dist-info/RECORD
