Metadata-Version: 2.1
Name: myredditdl
Version: 0.0.7
Summary: Reddit upvoted and saved media downloader
Home-page: https://github.com/emanuel2718/myredditdl
Author: Emanuel Ramirez Alsina
Author-email: eramirez2718@gmail.com
Maintainer: Emanuel Ramirez Alsina
Maintainer-email: eramirez2718@gmail.com
License: MIT
Keywords: myredditdl reddit downloader command line
Platform: UNKNOWN
Classifier: Development Status :: 3 - Alpha
Classifier: Environment :: Console
Classifier: Intended Audience :: Developers
Classifier: Programming Language :: Python :: 3
Classifier: Programming Language :: Python :: 3.6
Classifier: Programming Language :: Python :: 3.7
Classifier: Programming Language :: Python :: 3.8
Classifier: Programming Language :: Python :: 3.9
Classifier: Topic :: Documentation
Requires-Python: >=3.6
License-File: LICENSE
Requires-Dist: requests
Requires-Dist: praw
